{"chunk_definitions":[{"row":11,"row_count":1,"visible":true,"expansion_state":0,"options":{"engine":"r","label":"unnamed-chunk-1","dev":"png"},"document_id":"B330E310","chunk_id":"cmmnbz74359tf","chunk_label":"unnamed-chunk-1"},{"row":19,"row_count":1,"visible":true,"expansion_state":0,"options":{"engine":"r","label":"unnamed-chunk-2","dev":"png"},"document_id":"B330E310","chunk_id":"clj8alosf96ay","chunk_label":"unnamed-chunk-2"},{"row":42,"row_count":1,"visible":true,"expansion_state":0,"options":{"engine":"r","label":"unnamed-chunk-3","dev":"png"},"document_id":"B330E310","chunk_id":"c6q6t788kofo4","chunk_label":"unnamed-chunk-3"},{"row":52,"row_count":1,"visible":true,"expansion_state":0,"options":{"engine":"r","label":"unnamed-chunk-1","dev":"png"},"document_id":"B330E310","chunk_id":"ceixd6px57rzb","chunk_label":"unnamed-chunk-4"},{"row":63,"row_count":1,"visible":true,"expansion_state":0,"options":{"engine":"r","label":"unnamed-chunk-1","dev":"png"},"document_id":"B330E310","chunk_id":"cffaj5vul43bm","chunk_label":"unnamed-chunk-5"},{"row":83,"row_count":1,"visible":true,"expansion_state":0,"options":{"engine":"r","label":"unnamed-chunk-2","dev":"png"},"document_id":"B330E310","chunk_id":"cm9addc6c70us","chunk_label":"unnamed-chunk-6"},{"row":87,"row_count":1,"visible":true,"expansion_state":0,"options":{"engine":"r","label":"unnamed-chunk-1","dev":"png"},"document_id":"B330E310","chunk_id":"coo82sg4prs30","chunk_label":"unnamed-chunk-7"},{"row":93,"row_count":1,"visible":true,"expansion_state":0,"options":{"engine":"r","label":"unnamed-chunk-3","dev":"png"},"document_id":"B330E310","chunk_id":"cr42upyye08ot","chunk_label":"unnamed-chunk-8"},{"row":100,"row_count":1,"visible":true,"expansion_state":0,"options":{"engine":"r","label":"unnamed-chunk-2","dev":"png"},"document_id":"B330E310","chunk_id":"c8ib70f8sxp9x","chunk_label":"unnamed-chunk-9"},{"row":106,"row_count":1,"visible":true,"expansion_state":0,"options":{"engine":"r","label":"unnamed-chunk-2","dev":"png"},"document_id":"B330E310","chunk_id":"cdmacey42mu05","chunk_label":"unnamed-chunk-10"},{"row":114,"row_count":1,"visible":true,"expansion_state":0,"options":{"engine":"r","label":"unnamed-chunk-4","dev":"png"},"document_id":"B330E310","chunk_id":"coicofuy48zlx","chunk_label":"unnamed-chunk-11"},{"row":125,"row_count":1,"visible":true,"expansion_state":0,"options":{"engine":"r","label":"unnamed-chunk-5","dev":"png"},"document_id":"B330E310","chunk_id":"cn71894xbe05x","chunk_label":"unnamed-chunk-12"},{"row":149,"row_count":1,"visible":true,"expansion_state":0,"options":{"engine":"r","label":"unnamed-chunk-2","dev":"png"},"document_id":"B330E310","chunk_id":"cj9glqkhmxc41","chunk_label":"unnamed-chunk-14"},{"row":159,"row_count":1,"visible":true,"expansion_state":0,"options":{"engine":"r","label":"unnamed-chunk-5","dev":"png"},"document_id":"B330E310","chunk_id":"c4d0xrd1w7jp6","chunk_label":"unnamed-chunk-15"}],"doc_write_time":1721903673}